examples/__init__.py
examples/bbuffer.py
examples/ovftool.py
examples/party.py
examples/stock.py
pali/__init__.py
pali/bbuffer.py
pali/common.py
pali/config.py
pali/console.py
pali/constants.py
pali/logger.py
pali/parallel.py
pali/params.py
pali/pipeline.py
pali/task.py
pali/thread.py
pali/worker.py
tests/__init__.py
tests/test_bbuffer.py
tests/test_config.py
tests/test_param.py
tests/test_task.py
tests/test_tp_workers.py
tests/test_worker.py
tests/test_worker_pool.py
tests/test_wp_scale.py
pali-0.0.7.dist-info/LICENSE
pali-0.0.7.dist-info/METADATA
pali-0.0.7.dist-info/WHEEL
pali-0.0.7.dist-info/top_level.txt
pali-0.0.7.dist-info/RECORD
