Metadata-Version: 2.1
Name: pali
Version: 0.0.7
Summary: A simple ThreadPool library
Home-page: https://github.com/gitvipin/pali
Author: Vipin Sharma
Author-email: sh.vipin@gmail.com
License: UNKNOWN
Platform: UNKNOWN
Classifier: Programming Language :: Python :: 2
Classifier: License :: OSI Approved :: MIT License
Classifier: Operating System :: OS Independent
